djangoldp_event/__init__.py
djangoldp_event/admin.py
djangoldp_event/apps.py
djangoldp_event/djangoldp_urls.py
djangoldp_event/factories.py
djangoldp_event/models.py
djangoldp_event/views.py
djangoldp_event/management/__init__.py
djangoldp_event/management/commands/__init__.py
djangoldp_event/management/commands/mock_example.py
djangoldp_event/migrations/0001_initial.py
djangoldp_event/migrations/0002_auto_20200202_1639.py
djangoldp_event/migrations/0003_auto_20200202_1644.py
djangoldp_event/migrations/0004_auto_20200202_2110.py
djangoldp_event/migrations/0004_auto_20200426_1603.py
djangoldp_event/migrations/0005_auto_20200617_1458.py
djangoldp_event/migrations/0006_auto_20200709_1411.py
djangoldp_event/migrations/0007_merge_20200812_0928.py
djangoldp_event/migrations/0008_merge_20200812_1009.py
djangoldp_event/migrations/0009_auto_20200812_1446.py
djangoldp_event/migrations/0010_auto_20200812_1459.py
djangoldp_event/migrations/0011_auto_20200923_1017.py
djangoldp_event/migrations/0012_event_author.py
djangoldp_event/migrations/0013_auto_20210525_1018.py
djangoldp_event/migrations/0014_auto_20210525_1022.py
djangoldp_event/migrations/0015_event_visible.py
djangoldp_event/migrations/0016_auto_20210527_1612.py
djangoldp_event/migrations/0017_auto_20221012_1503.py
djangoldp_event/migrations/0018_alter_event_options_alter_locationevent_options_and_more.py
djangoldp_event/migrations/0019_add_timestamps_to_models.py
djangoldp_event/migrations/__init__.py
djangoldp_event-5.0.0.dist-info/METADATA
djangoldp_event-5.0.0.dist-info/WHEEL
djangoldp_event-5.0.0.dist-info/top_level.txt
djangoldp_event-5.0.0.dist-info/RECORD
