Metadata-Version: 2.4
Name: djangoldp_event
Version: 5.0.0
Summary: djangoldp event package
Home-page: https://git.startinblox.com/djangoldp-packages/djangoldp-event
Author: Startin'blox
Author-email: contact@startinblox.com
License: MIT
Requires-Dist: djangoldp~=5.0.0
Requires-Dist: djangoldp_circle~=5.0.0
Provides-Extra: dev
Requires-Dist: factory_boy>=2.11.0; extra == "dev"
